django_fieldbustier/__init__.py
django_fieldbustier/apps.py
django_fieldbustier/fieldbustier_config.py
django_fieldbustier/urls.py
django_fieldbustier/version.py
django_fieldbustier-0.8.0.dist-info/LICENSE
django_fieldbustier-0.8.0.dist-info/METADATA
django_fieldbustier-0.8.0.dist-info/WHEEL
django_fieldbustier-0.8.0.dist-info/top_level.txt
django_fieldbustier-0.8.0.dist-info/RECORD
