Metadata-Version: 2.1
Name: django-fieldbustier
Version: 0.8.0
Summary: A package that allows modifying a model of any django app from the outside, without modifying the code of the app itself.
Home-page: https://github.com/mrjmad/django-fieldbustier
Author: MrJmad
Author-email: j-mad@j-mad.com
License: MIT License
Platform: UNKNOWN
Classifier: Programming Language :: Python :: 3
Classifier: License :: OSI Approved :: MIT License
Classifier: Development Status :: 4 - Beta
Classifier: Environment :: Web Environment
Classifier: Framework :: Django
Classifier: Intended Audience :: Information Technology
Classifier: Operating System :: OS Independent
Classifier: Topic :: Internet :: WWW/HTTP
